flotils/__init__.py
flotils/convenience.py
flotils/loadable.py
flotils/logable.py
flotils/runable.py
flotils-0.5.3.dist-info/AUTHORS.rst
flotils-0.5.3.dist-info/LICENSE
flotils-0.5.3.dist-info/METADATA
flotils-0.5.3.dist-info/WHEEL
flotils-0.5.3.dist-info/top_level.txt
flotils-0.5.3.dist-info/RECORD
