Metadata-Version: 2.1
Name: flotils
Version: 0.5.3
Summary: Utility functions and classes
Home-page: https://github.com/the01/python-flotils
Author: the01
Author-email: jungflor@gmail.com
License: MIT License
Keywords: flotils logging wrapper loading json baseclass
Platform: UNKNOWN
Classifier: Development Status :: 4 - Beta
Classifier: Intended Audience :: Developers
Classifier: License :: OSI Approved :: MIT License
Classifier: Natural Language :: English
Classifier: Programming Language :: Python :: 2
Classifier: Programming Language :: Python :: 2.7
Classifier: Programming Language :: Python :: 3
Classifier: Programming Language :: Python :: 3.5
Classifier: Programming Language :: Python :: 3.6
Classifier: Programming Language :: Python :: 3.7
Requires-Dist: wheel (>=0.26.0)
Requires-Dist: colorlog (==2.7.0)
Requires-Dist: pyyaml (<6.0,>=5.1)
